gsubmit.py
graphite_submit_mod-0.0.1.dist-info/LICENSE
graphite_submit_mod-0.0.1.dist-info/METADATA
graphite_submit_mod-0.0.1.dist-info/WHEEL
graphite_submit_mod-0.0.1.dist-info/top_level.txt
graphite_submit_mod-0.0.1.dist-info/RECORD
